Metadata-Version: 2.1
Name: odoo14-addon-shopinvader-locomotive-reset-password
Version: 14.0.1.3.0
Summary: Give the possibility to send a email to reset thepassword from odoo
Home-page: https://github.com/shopinvader/odoo-shopinvader
Author: Akretion
License: AGPL-3
Platform: UNKNOWN
Classifier: Programming Language :: Python
Classifier: Framework :: Odoo
Classifier: Framework :: Odoo :: 14.0
Classifier: License :: OSI Approved :: GNU Affero General Public License v3
Requires-Python: >=3.6
Requires-Dist: odoo14-addon-shopinvader-locomotive
Requires-Dist: odoo (<14.1dev,>=14.0a)
